fishlifetraits/__init__.py
fishlifetraits/stats.py
fishlifetraits/utils.py
fishlifetraits-0.7.dist-info/LICENSE
fishlifetraits-0.7.dist-info/METADATA
fishlifetraits-0.7.dist-info/WHEEL
fishlifetraits-0.7.dist-info/top_level.txt
fishlifetraits-0.7.dist-info/RECORD
