Metadata-Version: 2.1
Name: fishlifetraits
Version: 0.7
Maintainer: Ulises Rosas
Maintainer-email: ulisesfrosasp@gmail.com
Classifier: Programming Language :: Python :: 3
License-File: LICENSE
Requires-Dist: dendropy ==4.4.0
Requires-Dist: scipy
Requires-Dist: numpy
